{
  "worldId": 4,
  "levelId": 4,
  "launchPosition": {
    "x": 0.08,
    "y": 0.5
  },
  "launchVelocity": {
    "dx": 150.5,
    "dy": -8.7
  },
  "goalPosition": {
    "x": 0.9,
    "y": 0.355
  },
  "goalRadius": 32,
  "initialGravityDown": true,
  "parFlips": 4,
  "parTime": 3.2,
  "obstacles": [
    {
      "id": "top-bar",
      "type": "rect",
      "position": {
        "x": 0.5,
        "y": 0.06
      },
      "size": {
        "width": 1.0,
        "height": 0.018
      },
      "rotation": 0,
      "style": "solid"
    },
    {
      "id": "bot-bar",
      "type": "rect",
      "position": {
        "x": 0.5,
        "y": 0.94
      },
      "size": {
        "width": 1.0,
        "height": 0.018
      },
      "rotation": 0,
      "style": "solid"
    },
    {
      "id": "obs-1",
      "type": "rect",
      "position": {
        "x": 0.247,
        "y": 0.188
      },
      "size": {
        "width": 0.073,
        "height": 0.1
      },
      "rotation": 4.0,
      "style": "solid"
    },
    {
      "id": "obs-2",
      "type": "rect",
      "position": {
        "x": 0.39,
        "y": 0.724
      },
      "size": {
        "width": 0.071,
        "height": 0.091
      },
      "rotation": -2.6,
      "style": "solid"
    },
    {
      "id": "obs-3",
      "type": "rect",
      "position": {
        "x": 0.565,
        "y": 0.221
      },
      "size": {
        "width": 0.055,
        "height": 0.092
      },
      "rotation": -7.1,
      "style": "solid"
    },
    {
      "id": "obs-4",
      "type": "rect",
      "position": {
        "x": 0.803,
        "y": 0.681
      },
      "size": {
        "width": 0.077,
        "height": 0.098
      },
      "rotation": 2.6,
      "style": "solid"
    }
  ],
  "collectibles": [
    {
      "position": {
        "x": 0.14,
        "y": 0.518
      }
    },
    {
      "position": {
        "x": 0.313,
        "y": 0.51
      }
    },
    {
      "position": {
        "x": 0.5,
        "y": 0.497
      }
    }
  ]
}
