{
  "worldId": 4,
  "levelId": 7,
  "launchPosition": {
    "x": 0.08,
    "y": 0.5
  },
  "launchVelocity": {
    "dx": 227.1,
    "dy": 0
  },
  "goalPosition": {
    "x": 0.9,
    "y": 0.595
  },
  "goalRadius": 31,
  "initialGravityDown": true,
  "parFlips": 8,
  "parTime": 1.6,
  "obstacles": [
    {
      "id": "top-bar",
      "type": "rect",
      "position": {
        "x": 0.5,
        "y": 0.06
      },
      "size": {
        "width": 1.0,
        "height": 0.018
      },
      "rotation": 0,
      "style": "solid"
    },
    {
      "id": "bot-bar",
      "type": "rect",
      "position": {
        "x": 0.5,
        "y": 0.94
      },
      "size": {
        "width": 1.0,
        "height": 0.018
      },
      "rotation": 0,
      "style": "solid"
    },
    {
      "id": "obs-1",
      "type": "rect",
      "position": {
        "x": 0.176,
        "y": 0.422
      },
      "size": {
        "width": 0.047,
        "height": 0.191
      },
      "rotation": 14.3,
      "style": "solid"
    },
    {
      "id": "obs-2",
      "type": "rect",
      "position": {
        "x": 0.311,
        "y": 0.682
      },
      "size": {
        "width": 0.035,
        "height": 0.233
      },
      "rotation": 16.8,
      "style": "solid"
    },
    {
      "id": "obs-4",
      "type": "rect",
      "position": {
        "x": 0.495,
        "y": 0.587
      },
      "size": {
        "width": 0.041,
        "height": 0.267
      },
      "rotation": 4.0,
      "style": "solid"
    },
    {
      "id": "obs-5",
      "type": "rect",
      "position": {
        "x": 0.62,
        "y": 0.375
      },
      "size": {
        "width": 0.039,
        "height": 0.148
      },
      "rotation": -7.8,
      "style": "solid"
    },
    {
      "id": "obs-7",
      "type": "rect",
      "position": {
        "x": 0.796,
        "y": 0.21
      },
      "size": {
        "width": 0.057,
        "height": 0.269
      },
      "rotation": -19.5,
      "style": "solid"
    }
  ],
  "collectibles": [
    {
      "position": {
        "x": 0.128,
        "y": 0.853
      }
    },
    {
      "position": {
        "x": 0.403,
        "y": 0.384
      }
    },
    {
      "position": {
        "x": 0.708,
        "y": 0.178
      }
    }
  ]
}
